pypcd/__init__.py
pypcd/nea_pc_format.py
pypcd/numpy_pc2.py
pypcd/pdutil.py
pypcd/pypcd.py
pypcd/sautil.py
pypcd/version.py
pypcd/tests/__init__.py
pypcd/tests/test_pypcd.py
pypcd3-0.1.1.dist-info/LICENSE
pypcd3-0.1.1.dist-info/METADATA
pypcd3-0.1.1.dist-info/WHEEL
pypcd3-0.1.1.dist-info/top_level.txt
pypcd3-0.1.1.dist-info/RECORD
