Metadata-Version: 2.1
Name: pypcd3
Version: 0.1.1
Summary: Pure Python PCD reader/writer
Home-page: http://github.com/dimatura/pypcd
Download-URL: 
Author: Daniel Maturana and other
Author-email: 
Maintainer: Daniel Maturana and other
Maintainer-email: 
License: MIT
Platform: OS Independent
Classifier: Development Status :: 3 - Alpha
Classifier: Environment :: Console
Classifier: Intended Audience :: Science/Research
Classifier: License :: OSI Approved :: MIT License
Classifier: Operating System :: OS Independent
Classifier: Programming Language :: Python
Classifier: Topic :: Scientific/Engineering
License-File: LICENSE
Requires-Dist: numpy
Requires-Dist: python-lzf
